<?xml version="1.0" encoding="UTF-8"?>
<metadata xml:lang="en"><Esri><CreaDate>20181030</CreaDate><CreaTime>14561400</CreaTime><ArcGISFormat>1.0</ArcGISFormat><SyncOnce>TRUE</SyncOnce><DataProperties><itemProps><itemLocation><linkage Sync="TRUE">file://\\10.0.1.18\groups\GIS\GIS_DATA\Transportation\Lime Network Analyst\Sept_destinations</linkage><protocol Sync="TRUE">Local Area Network</protocol></itemLocation></itemProps><copyHistory><copy source="F:\GIS\PROJECTS\Transportation\Active Transportation\Data\Lime Data\Sept_destinations" dest="\\10.0.1.18\groups\GIS\GIS_DATA\Transportation\Lime Network Analyst\Sept_destinations" date="20181030" time="14561400"></copy></copyHistory></DataProperties></Esri></metadata>
